gigavector/__init__.py
gigavector/_core.py
gigavector/_ffi.py
gigavector/libGigaVector.so
gigavector/py.typed
gigavector-0.7.0.dist-info/licenses/LICENCE.md
gigavector-0.7.0.dist-info/METADATA
gigavector-0.7.0.dist-info/WHEEL
gigavector-0.7.0.dist-info/top_level.txt
gigavector-0.7.0.dist-info/RECORD
