Metadata-Version: 2.4
Name: gigavector
Version: 0.7.0
Summary: High-performance vector database library for Python with multiple index types and metadata support
Author: GigaVector Maintainers
License: # THE "DON'T BE A JERK" GENERAL PUBLIC LICENSE (DBaJ-GPL)
Project-URL: Homepage, https://github.com/jaywyawhare/GigaVector
Project-URL: Repository, https://github.com/jaywyawhare/GigaVector
Classifier: License :: Other/Proprietary License
Classifier: Programming Language :: Python :: 3
Classifier: Programming Language :: Python :: 3 :: Only
Classifier: Programming Language :: Python :: 3.9
Classifier: Programming Language :: Python :: 3.10
Classifier: Programming Language :: Python :: 3.11
Classifier: Programming Language :: Python :: 3.12
Classifier: Programming Language :: C
Requires-Python: >=3.9
License-File: LICENCE.md
Requires-Dist: cffi>=1.16
Dynamic: license-file
